[{"id":"efb1008e-81e2-4b61-a210-9685581ea16b","note":"\n            \n            \n            \n            \n            \n            \n            \n            \n            \n            \n            \n            \n            \n            \n            \n            \n            \n            \n            \n                \n                \n            \n            Lorem ipsum dolor sit amet, consectetur adipiscing elit. Nulla ultricies eleifend ligula, ac mattis mauris auctor in. Aliquam egestas elementum ultrices. Phasellus ut blandit odio. Morbi eleifend risus eu eros gravida, id iaculis lorem egestas. Nulla id neque magna. Aliquam iaculis nibh sit amet diam congue, vitae ornare velit consectetur. Maecenas finibus felis est, at eleifend ipsum vulputate quis.\n        \n            \n            \n        \n        \n        \n        \n        \n        \n        \n        \n        \n        \n        \n        \n        \n        \n        \n        \n        \n        \n        ","linkType":"story","linkId":1,"date":"2017-01-04T02:40:56.926Z"},{"id":"c731751c-1c79-4f2f-bf87-b35d825b958a","note":"Bar","date":"2017-01-07T05:40:19.973Z"},{"id":"32649c3b-ee38-401f-a6e0-ed3fe49014b2","note":"This is another note for \"Out Hero\"","linkType":"story","linkId":1,"date":"2017-01-07T19:04:52.606Z"},{"id":"00cc970e-234a-4d29-ae84-205a5c6c4a60","note":"The imperials aren't coming.  Instead, they are moving to fence in the ridge.  They are already camped out down below, and a team of several guards, attack dogs and one mage is approaching the top of the ridge from the northeast.  The mage is clearly high level - an attack is clearly not viable.  Attempting to attack will result in the player being captured, interrogated, and shipped off a siege fodder on the front lines.The mage arrived at the small outpost 10 miles up the road within hours of the player's encounter on the ridge.  He ordered all soldiers at the post to accompany him to the ridge, leaving the post abandoned.  If the player stays to observe, she will see the mage sweep the ridge with fireballs, the magical equivalent of an artillery strike.","linkType":"story","linkId":2,"date":"2017-01-16T18:31:51.879Z"},{"id":"9143ad62-1196-4e31-900b-20c841805212","note":"The player can continue up to the abandoned post, where she will find supplies, documents and a small copper sphere.","linkType":"story","linkId":2,"date":"2017-01-16T18:36:30.392Z"},{"id":"19ebf8c5-6122-462a-9578-4192b1f68c49","note":"The Wizard Marshall's name is Margrave Olaf Callister.  The sphere is a penny rider (slang). Penny rider references riders who carry messages between noble estates for a \"penny\" (small wages).  The riders provided a very fast method of delivering information or light goods in the absence of magic.","linkType":"story","linkId":2,"date":"2017-01-16T18:54:05.259Z"}]